{
	"credit": "Made with Blockbench",
	"textures": {
		"0": "models/koucyacya",
		"particle": "models/koucyacya"
	},
	"elements": [
		{
			"from": [7.68508, 6.48127, 5.31302],
			"to": [10.0419, 8.83799, 7.66973],
			"rotation": {"angle": 0, "axis": "y", "origin": [19.1746, 18.56, 23.87302]},
			"faces": {
				"north": {"uv": [2, 2, 4, 4], "texture": "#0"},
				"east": {"uv": [0, 2, 2, 4], "texture": "#0"},
				"south": {"uv": [6, 2, 8, 4], "texture": "#0"},
				"west": {"uv": [4, 2, 6, 4], "texture": "#0"},
				"up": {"uv": [2, 0, 4, 2], "texture": "#0"},
				"down": {"uv": [2, 2, 4, 4], "texture": "#0"}
			}
		},
		{
			"from": [10.16888, 6.48127, 5.31302],
			"to": [10.16888, 8.83799, 7.66973],
			"rotation": {"angle": 0, "axis": "y", "origin": [19.1746, 18.56, 23.87302]},
			"faces": {
				"north": {"uv": [2, 2, 4, 4], "texture": "#0"},
				"east": {"uv": [8, 2, 10, 4], "texture": "#0"},
				"south": {"uv": [6, 2, 8, 4], "texture": "#0"},
				"west": {"uv": [4, 2, 6, 4], "texture": "#0"},
				"up": {"uv": [2, 0, 4, 2], "texture": "#0"},
				"down": {"uv": [2, 2, 4, 4], "texture": "#0"}
			}
		},
		{
			"from": [7.5581, 6.48127, 5.31302],
			"to": [7.5581, 8.83799, 7.66973],
			"rotation": {"angle": 0, "axis": "y", "origin": [19.1746, 18.56, 23.87302]},
			"faces": {
				"north": {"uv": [2, 2, 4, 4], "texture": "#0"},
				"east": {"uv": [0, 2, 2, 4], "texture": "#0"},
				"south": {"uv": [6, 2, 8, 4], "texture": "#0"},
				"west": {"uv": [12.5, 2, 14.5, 4], "texture": "#0"},
				"up": {"uv": [2, 0, 4, 2], "texture": "#0"},
				"down": {"uv": [2, 2, 4, 4], "texture": "#0"}
			}
		},
		{
			"from": [7.68508, 6.48127, 5.18604],
			"to": [10.0419, 8.83799, 5.18604],
			"rotation": {"angle": 0, "axis": "y", "origin": [19.1746, 18.56, 23.87302]},
			"faces": {
				"north": {"uv": [10, 1.75, 12, 3.75], "texture": "#0"},
				"east": {"uv": [0, 2, 2, 4], "texture": "#0"},
				"south": {"uv": [14, 11.25, 16, 13.25], "texture": "#0"},
				"west": {"uv": [4, 2, 6, 4], "texture": "#0"},
				"up": {"uv": [2, 0, 4, 2], "texture": "#0"},
				"down": {"uv": [2, 2, 4, 4], "texture": "#0"}
			}
		},
		{
			"from": [7.68508, 8.98759, 5.31302],
			"to": [10.0419, 8.98759, 7.66973],
			"rotation": {"angle": 0, "axis": "y", "origin": [19.1746, 18.56, 23.87302]},
			"faces": {
				"north": {"uv": [2, 2, 4, 4], "texture": "#0"},
				"east": {"uv": [0, 2, 2, 4], "texture": "#0"},
				"south": {"uv": [6, 2, 8, 4], "texture": "#0"},
				"west": {"uv": [4, 2, 6, 4], "texture": "#0"},
				"up": {"uv": [10, 0, 12, 2], "texture": "#0"},
				"down": {"uv": [10, 0, 12, 2], "texture": "#0"}
			}
		},
		{
			"from": [10.0419, 2.94603, 5.90222],
			"to": [11.22032, 6.48116, 7.08053],
			"rotation": {"angle": 0, "axis": "y", "origin": [19.1746, 18.56, 23.87302]},
			"faces": {
				"north": {"uv": [11.25, 5, 13.282, 8.016], "texture": "#0"},
				"east": {"uv": [11.25, 5, 13.282, 8.016], "texture": "#0"},
				"south": {"uv": [10.5, 5, 12.532, 8.016], "texture": "#0"},
				"west": {"uv": [12, 5, 14.032, 8.016], "texture": "#0"},
				"up": {"uv": [10.75, 5, 12.532, 7.016], "texture": "#0"},
				"down": {"uv": [4.60352, 1.14844, 5.35352, 1.89844], "texture": "#0"}
			}
		},
		{
			"from": [9.1581, 1.80392, 2.34231],
			"to": [10.33651, 2.98223, 5.87745],
			"rotation": {"angle": -22.5, "axis": "y", "origin": [8.86346, 2.40538, 5.30065]},
			"faces": {
				"north": {"uv": [2, 4, 2.9695, 4.98475], "rotation": 180, "texture": "#0"},
				"east": {"uv": [0, 5, 1.157, 8.016], "rotation": 270, "texture": "#0"},
				"south": {"uv": [1.5, 5, 2.907, 8.016], "texture": "#0"},
				"west": {"uv": [1.5, 5, 2.907, 8], "rotation": 90, "texture": "#0"},
				"up": {"uv": [0.25, 5, 2.282, 8.016], "rotation": 180, "texture": "#0"},
				"down": {"uv": [3.03125, 5, 3.93825, 8.016], "texture": "#0"}
			}
		},
		{
			"from": [6.71258, 1.80392, 2.77118],
			"to": [7.89099, 2.98223, 6.30632],
			"rotation": {"angle": 22.5, "axis": "y", "origin": [7.30179, 2.39308, 4.53875]},
			"faces": {
				"north": {"uv": [2.9695, 4, 2, 4.98475], "rotation": 180, "texture": "#0"},
				"east": {"uv": [1.5, 8, 2.907, 5], "rotation": 90, "texture": "#0"},
				"south": {"uv": [2.907, 5, 1.5, 8.016], "texture": "#0"},
				"west": {"uv": [0, 8.016, 1.157, 5], "rotation": 270, "texture": "#0"},
				"up": {"uv": [2.282, 5, 0.25, 8.016], "rotation": 180, "texture": "#0"},
				"down": {"uv": [3.93825, 5, 3.03125, 8.016], "texture": "#0"}
			}
		},
		{
			"from": [7.68508, 2.94592, 5.90222],
			"to": [10.0419, 6.48116, 7.08053],
			"rotation": {"angle": 0, "axis": "y", "origin": [19.1746, 18.56, 23.87302]},
			"faces": {
				"north": {"uv": [5, 5, 7.032, 8.016], "texture": "#0"},
				"east": {"uv": [4.25, 5, 6.282, 8.016], "texture": "#0"},
				"south": {"uv": [8, 5, 10.032, 8.016], "texture": "#0"},
				"west": {"uv": [5, 5, 7.032, 8.016], "texture": "#0"},
				"up": {"uv": [5, 5, 7.032, 8.016], "texture": "#0"},
				"down": {"uv": [5, 5, 7.032, 8.016], "texture": "#0"}
			}
		},
		{
			"from": [7.68508, 2.94592, 7.20751],
			"to": [10.0419, 6.48116, 7.20751],
			"rotation": {"angle": 0, "axis": "y", "origin": [19.1746, 18.56, 23.87302]},
			"faces": {
				"north": {"uv": [5, 5, 7.032, 8.016], "texture": "#0"},
				"east": {"uv": [4.25, 5, 6.282, 8.016], "texture": "#0"},
				"south": {"uv": [7.75, 9, 9.782, 12.016], "texture": "#0"},
				"west": {"uv": [5, 5, 7.032, 8.016], "texture": "#0"},
				"up": {"uv": [5, 5, 7.032, 8.016], "texture": "#0"},
				"down": {"uv": [5, 5, 7.032, 8.016], "texture": "#0"}
			}
		},
		{
			"from": [7.68508, 2.35672, 5.90222],
			"to": [10.0419, 2.94592, 7.08053],
			"rotation": {"angle": 0, "axis": "y", "origin": [19.1746, 18.56, 23.87302]},
			"faces": {
				"north": {"uv": [10.5, 6, 11.25, 6.75], "texture": "#0"},
				"east": {"uv": [10.5, 6, 11.25, 6.75], "texture": "#0"},
				"south": {"uv": [10.5, 6, 11.25, 6.75], "texture": "#0"},
				"west": {"uv": [10.5, 6, 11.25, 6.75], "texture": "#0"},
				"up": {"uv": [10.5, 6, 11.25, 6.75], "texture": "#0"},
				"down": {"uv": [10.5, 6, 11.25, 6.75], "texture": "#0"}
			}
		},
		{
			"from": [6.50667, 2.94603, 5.90222],
			"to": [7.68508, 6.48116, 7.08053],
			"rotation": {"angle": 0, "axis": "y", "origin": [19.1746, 18.56, 23.87302]},
			"faces": {
				"north": {"uv": [10, 5, 12.032, 8.016], "texture": "#0"},
				"east": {"uv": [10, 5, 12.032, 8.016], "texture": "#0"},
				"south": {"uv": [10, 5, 12.032, 8.016], "texture": "#0"},
				"west": {"uv": [10, 5, 12.032, 8.016], "texture": "#0"},
				"up": {"uv": [10, 5, 12.032, 6.516], "texture": "#0"},
				"down": {"uv": [4.60352, 1.14844, 5.38552, 1.91444], "texture": "#0"}
			}
		}
	],
	"display": {
		"thirdperson_righthand": {
			"rotation": [90, 0, 0],
			"translation": [-0.5, -2.75, 17.75]
		},
		"thirdperson_lefthand": {
			"rotation": [90, 0, 0],
			"translation": [1, -2.75, 17.75]
		},
		"firstperson_righthand": {
			"translation": [7.75, -4, 0]
		},
		"firstperson_lefthand": {
			"translation": [7.75, -4, 0]
		},
		"ground": {
			"translation": [5.5, 6.5, 7.5]
		},
		"gui": {
			"rotation": [0, 180, 0],
			"translation": [-16.5, 23.25, 0],
			"scale": [2, 2, 2]
		},
		"head": {
			"translation": [-2, 18.25, 5],
			"scale": [2, 2, 2]
		}
	}
}
